swift_f0/__init__.py
swift_f0/core.py
swift_f0/model.onnx
swift_f0/music.py
swift_f0-0.1.2.dist-info/licenses/LICENSE
swift_f0-0.1.2.dist-info/METADATA
swift_f0-0.1.2.dist-info/WHEEL
swift_f0-0.1.2.dist-info/top_level.txt
swift_f0-0.1.2.dist-info/RECORD
