Metadata-Version: 2.4
Name: swift-f0
Version: 0.1.2
Summary: Fast and accurate fundamental frequency (F0) detector using convolutional neural networks
Author-email: Lars Nieradzik <l.nieradzik@gmail.com>
License-Expression: MIT
Project-URL: Homepage, https://github.com/lars76/swift-f0
Project-URL: Bug Reports, https://github.com/lars76/swift-f0/issues
Project-URL: Source, https://github.com/lars76/swift-f0
Keywords: pitch detection,fundamental frequency,audio analysis,speech processing,F0
Classifier: Development Status :: 4 - Beta
Classifier: Intended Audience :: Developers
Classifier: Intended Audience :: Science/Research
Classifier: Operating System :: OS Independent
Classifier: Programming Language :: Python :: 3
Classifier: Programming Language :: Python :: 3.8
Classifier: Programming Language :: Python :: 3.9
Classifier: Programming Language :: Python :: 3.10
Classifier: Programming Language :: Python :: 3.11
Classifier: Programming Language :: Python :: 3.12
Classifier: Topic :: Scientific/Engineering :: Artificial Intelligence
Classifier: Topic :: Multimedia :: Sound/Audio :: Analysis
Classifier: Topic :: Multimedia :: Sound/Audio :: MIDI
Requires-Python: >=3.8
License-File: LICENSE
Requires-Dist: onnxruntime
Requires-Dist: numpy
Provides-Extra: full
Requires-Dist: librosa; extra == "full"
Requires-Dist: matplotlib; extra == "full"
Requires-Dist: mido; extra == "full"
Provides-Extra: audio
Requires-Dist: librosa; extra == "audio"
Provides-Extra: viz
Requires-Dist: matplotlib; extra == "viz"
Provides-Extra: midi
Requires-Dist: mido; extra == "midi"
Provides-Extra: music
Requires-Dist: mido; extra == "music"
Requires-Dist: matplotlib; extra == "music"
Dynamic: license-file
